[
  {
    "id": 10010101,
    "action_type": 1,
    "time": 12,
    "target_type": 1,
    "area_center": 0,
    "area_radius": 0,
    "bullet": 0,
    "buffId": 0,
    "ratio": 1,
    "effect": 0,
    "audio": 0
  },
  {
    "id": 10010102,
    "action_type": 1,
    "time": 500,
    "target_type": 2,
    "area_center": 1,
    "area_radius": 3,
    "bullet": 0,
    "buffId": 0,
    "ratio": 0.3,
    "effect": 0,
    "audio": 0
  },
  {
    "id": 10010103,
    "action_type": 100,
    "time": 500,
    "target_type": 0,
    "area_center": 0,
    "area_radius": 0,
    "bullet": 0,
    "buffId": 0,
    "ratio": 0,
    "effect": 1,
    "audio": 0
  },
  {
    "id": 10010104,
    "action_type": 1,
    "time": 1000,
    "target_type": 2,
    "area_center": 1,
    "area_radius": 3,
    "bullet": 0,
    "buffId": 0,
    "ratio": 0.3,
    "effect": 0,
    "audio": 0
  },
  {
    "id": 10010105,
    "action_type": 100,
    "time": 1000,
    "target_type": 0,
    "area_center": 0,
    "area_radius": 0,
    "bullet": 0,
    "buffId": 0,
    "ratio": 0,
    "effect": 1,
    "audio": 0
  },
  {
    "id": 10020101,
    "action_type": 1,
    "time": 15,
    "target_type": 1,
    "area_center": 0,
    "area_radius": 0,
    "bullet": 1,
    "buffId": 0,
    "ratio": 1,
    "effect": 0,
    "audio": 0
  },
  {
    "id": 10020211,
    "action_type": 6,
    "time": 0,
    "target_type": 0,
    "area_center": 0,
    "area_radius": 0,
    "bullet": 0,
    "buffId": 0,
    "ratio": 0.1,
    "effect": 0,
    "audio": 0
  },
  {
    "id": 10210101,
    "action_type": 1,
    "time": 500,
    "target_type": 2,
    "area_center": 2,
    "area_radius": 3,
    "bullet": 2,
    "buffId": 0,
    "ratio": 1,
    "effect": 0,
    "audio": 0
  },
  {
    "id": 10210102,
    "action_type": 3,
    "time": 0,
    "target_type": 0,
    "area_center": 0,
    "area_radius": 0,
    "bullet": 0,
    "buffId": 10210102,
    "ratio": 0,
    "effect": 0,
    "audio": 0
  }
]